bf_monitor/__init__.py
bf_monitor/__main__.py
bf_monitor/cli.py
bf_monitor/driver.py
bf_monitor/utils.py
bf_monitor/version.txt
bf_monitor-0.0.5.dist-info/LICENSE
bf_monitor-0.0.5.dist-info/METADATA
bf_monitor-0.0.5.dist-info/WHEEL
bf_monitor-0.0.5.dist-info/entry_points.txt
bf_monitor-0.0.5.dist-info/top_level.txt
bf_monitor-0.0.5.dist-info/RECORD
