Metadata-Version: 2.1
Name: bf_monitor
Version: 0.0.5
Summary: filesystem monitor for b!
Home-page: https://github.com/txyliu/bf_monitor
Author: author 1, author 2
Author-email: your@email.com
Project-URL: Bug Tracker, https://github.com/txyliu/bf_monitor/issues
Classifier: Programming Language :: Python :: 3
Classifier: Operating System :: OS Independent
Requires-Python: >=3.11
License-File: LICENSE
